torch_linear_regression/__init__.py
torch_linear_regression/linear_regression.py
torch_linear_regression/utils.py
torch_linear_regression-0.1.0.dist-info/LICENSE
torch_linear_regression-0.1.0.dist-info/METADATA
torch_linear_regression-0.1.0.dist-info/WHEEL
torch_linear_regression-0.1.0.dist-info/top_level.txt
torch_linear_regression-0.1.0.dist-info/RECORD
