Metadata-Version: 2.1
Name: torch_linear_regression
Version: 0.1.0
Summary: A library of useful modules for data analysis.
Home-page: https://github.com/RichieHakim/torch_linear_regression
Author: Richard Hakim
License: LICENSE
Keywords: data analysis,machine learning,neuroscience
License-File: LICENSE
Requires-Dist: numpy
Requires-Dist: scikit-learn
Requires-Dist: torch
Requires-Dist: hypothesis
